{
    "description": "",
    "tags": [],
    "size": {
        "height": 1080,
        "width": 1920
    },
    "objects": [
        {
            "id": 553798901,
            "classId": 2703929,
            "description": "",
            "geometryType": "rectangle",
            "labelerLogin": "daan012",
            "createdAt": "2020-11-10T14:13:10.183Z",
            "updatedAt": "2020-11-10T14:13:39.823Z",
            "tags": [],
            "classTitle": "Head",
            "points": {
                "exterior": [
                    [
                        451,
                        249
                    ],
                    [
                        542,
                        357
                    ]
                ],
                "interior": []
            }
        },
        {
            "id": 553798910,
            "classId": 2703929,
            "description": "",
            "geometryType": "rectangle",
            "labelerLogin": "daan012",
            "createdAt": "2020-11-10T14:13:16.035Z",
            "updatedAt": "2020-11-10T14:13:39.823Z",
            "tags": [],
            "classTitle": "Head",
            "points": {
                "exterior": [
                    [
                        462,
                        475
                    ],
                    [
                        591,
                        611
                    ]
                ],
                "interior": []
            }
        },
        {
            "id": 553798919,
            "classId": 2703929,
            "description": "",
            "geometryType": "rectangle",
            "labelerLogin": "daan012",
            "createdAt": "2020-11-10T14:13:20.254Z",
            "updatedAt": "2020-11-10T14:13:39.823Z",
            "tags": [],
            "classTitle": "Head",
            "points": {
                "exterior": [
                    [
                        837,
                        218
                    ],
                    [
                        884,
                        295
                    ]
                ],
                "interior": []
            }
        },
        {
            "id": 553798925,
            "classId": 2703929,
            "description": "",
            "geometryType": "rectangle",
            "labelerLogin": "daan012",
            "createdAt": "2020-11-10T14:13:25.954Z",
            "updatedAt": "2020-11-10T14:13:39.823Z",
            "tags": [],
            "classTitle": "Head",
            "points": {
                "exterior": [
                    [
                        1297,
                        251
                    ],
                    [
                        1363,
                        331
                    ]
                ],
                "interior": []
            }
        },
        {
            "id": 553798944,
            "classId": 2703929,
            "description": "",
            "geometryType": "rectangle",
            "labelerLogin": "daan012",
            "createdAt": "2020-11-10T14:13:39.747Z",
            "updatedAt": "2020-11-10T14:13:39.747Z",
            "tags": [],
            "classTitle": "Head",
            "points": {
                "exterior": [
                    [
                        1851,
                        380
                    ],
                    [
                        1920,
                        509
                    ]
                ],
                "interior": []
            }
        }
    ]
}