{
    "description": "",
    "tags": [],
    "size": {
        "height": 1080,
        "width": 1920
    },
    "objects": [
        {
            "id": 553811993,
            "classId": 2703929,
            "description": "",
            "geometryType": "rectangle",
            "labelerLogin": "mathias.smeets222@gmail.com",
            "createdAt": "2020-11-10T15:04:34.175Z",
            "updatedAt": "2020-11-10T15:05:03.951Z",
            "tags": [],
            "classTitle": "Head",
            "points": {
                "exterior": [
                    [
                        1084,
                        813
                    ],
                    [
                        1304,
                        1054
                    ]
                ],
                "interior": []
            }
        },
        {
            "id": 553812007,
            "classId": 2703929,
            "description": "",
            "geometryType": "rectangle",
            "labelerLogin": "mathias.smeets222@gmail.com",
            "createdAt": "2020-11-10T15:04:42.136Z",
            "updatedAt": "2020-11-10T15:05:03.951Z",
            "tags": [],
            "classTitle": "Head",
            "points": {
                "exterior": [
                    [
                        654,
                        252
                    ],
                    [
                        743,
                        350
                    ]
                ],
                "interior": []
            }
        },
        {
            "id": 553812025,
            "classId": 2703929,
            "description": "",
            "geometryType": "rectangle",
            "labelerLogin": "mathias.smeets222@gmail.com",
            "createdAt": "2020-11-10T15:04:48.172Z",
            "updatedAt": "2020-11-10T15:05:03.951Z",
            "tags": [],
            "classTitle": "Head",
            "points": {
                "exterior": [
                    [
                        903,
                        198
                    ],
                    [
                        951,
                        265
                    ]
                ],
                "interior": []
            }
        },
        {
            "id": 553812041,
            "classId": 2703929,
            "description": "",
            "geometryType": "rectangle",
            "labelerLogin": "mathias.smeets222@gmail.com",
            "createdAt": "2020-11-10T15:04:52.187Z",
            "updatedAt": "2020-11-10T15:05:03.951Z",
            "tags": [],
            "classTitle": "Head",
            "points": {
                "exterior": [
                    [
                        1174,
                        168
                    ],
                    [
                        1236,
                        258
                    ]
                ],
                "interior": []
            }
        },
        {
            "id": 553812047,
            "classId": 2703929,
            "description": "",
            "geometryType": "rectangle",
            "labelerLogin": "mathias.smeets222@gmail.com",
            "createdAt": "2020-11-10T15:04:58.001Z",
            "updatedAt": "2020-11-10T15:05:03.951Z",
            "tags": [],
            "classTitle": "Head",
            "points": {
                "exterior": [
                    [
                        1627,
                        178
                    ],
                    [
                        1710,
                        277
                    ]
                ],
                "interior": []
            }
        },
        {
            "id": 553812054,
            "classId": 2703929,
            "description": "",
            "geometryType": "rectangle",
            "labelerLogin": "mathias.smeets222@gmail.com",
            "createdAt": "2020-11-10T15:05:03.888Z",
            "updatedAt": "2020-11-10T15:05:03.888Z",
            "tags": [],
            "classTitle": "Head",
            "points": {
                "exterior": [
                    [
                        1434,
                        373
                    ],
                    [
                        1530,
                        490
                    ]
                ],
                "interior": []
            }
        }
    ]
}