{
    "description": "",
    "tags": [],
    "size": {
        "height": 1080,
        "width": 1920
    },
    "objects": [
        {
            "id": 553811848,
            "classId": 2703929,
            "description": "",
            "geometryType": "rectangle",
            "labelerLogin": "mathias.smeets222@gmail.com",
            "createdAt": "2020-11-10T15:03:19.007Z",
            "updatedAt": "2020-11-10T15:03:51.592Z",
            "tags": [],
            "classTitle": "Head",
            "points": {
                "exterior": [
                    [
                        649,
                        250
                    ],
                    [
                        736,
                        342
                    ]
                ],
                "interior": []
            }
        },
        {
            "id": 553811861,
            "classId": 2703929,
            "description": "",
            "geometryType": "rectangle",
            "labelerLogin": "mathias.smeets222@gmail.com",
            "createdAt": "2020-11-10T15:03:24.355Z",
            "updatedAt": "2020-11-10T15:03:51.592Z",
            "tags": [],
            "classTitle": "Head",
            "points": {
                "exterior": [
                    [
                        913,
                        200
                    ],
                    [
                        965,
                        271
                    ]
                ],
                "interior": []
            }
        },
        {
            "id": 553811870,
            "classId": 2703929,
            "description": "",
            "geometryType": "rectangle",
            "labelerLogin": "mathias.smeets222@gmail.com",
            "createdAt": "2020-11-10T15:03:29.525Z",
            "updatedAt": "2020-11-10T15:03:51.592Z",
            "tags": [],
            "classTitle": "Head",
            "points": {
                "exterior": [
                    [
                        1175,
                        172
                    ],
                    [
                        1239,
                        259
                    ]
                ],
                "interior": []
            }
        },
        {
            "id": 553811897,
            "classId": 2703929,
            "description": "",
            "geometryType": "rectangle",
            "labelerLogin": "mathias.smeets222@gmail.com",
            "createdAt": "2020-11-10T15:03:38.099Z",
            "updatedAt": "2020-11-10T15:03:51.592Z",
            "tags": [],
            "classTitle": "Head",
            "points": {
                "exterior": [
                    [
                        1624,
                        198
                    ],
                    [
                        1702,
                        295
                    ]
                ],
                "interior": []
            }
        },
        {
            "id": 553811903,
            "classId": 2703929,
            "description": "",
            "geometryType": "rectangle",
            "labelerLogin": "mathias.smeets222@gmail.com",
            "createdAt": "2020-11-10T15:03:44.418Z",
            "updatedAt": "2020-11-10T15:03:51.592Z",
            "tags": [],
            "classTitle": "Head",
            "points": {
                "exterior": [
                    [
                        1434,
                        378
                    ],
                    [
                        1550,
                        494
                    ]
                ],
                "interior": []
            }
        },
        {
            "id": 553811927,
            "classId": 2703929,
            "description": "",
            "geometryType": "rectangle",
            "labelerLogin": "mathias.smeets222@gmail.com",
            "createdAt": "2020-11-10T15:03:51.528Z",
            "updatedAt": "2020-11-10T15:03:51.528Z",
            "tags": [],
            "classTitle": "Head",
            "points": {
                "exterior": [
                    [
                        1151,
                        802
                    ],
                    [
                        1379,
                        1041
                    ]
                ],
                "interior": []
            }
        }
    ]
}