{
    "description": "",
    "tags": [],
    "size": {
        "height": 1080,
        "width": 1920
    },
    "objects": [
        {
            "id": 553812426,
            "classId": 2703929,
            "description": "",
            "geometryType": "rectangle",
            "labelerLogin": "mathias.smeets222@gmail.com",
            "createdAt": "2020-11-10T15:12:10.257Z",
            "updatedAt": "2020-11-10T15:12:10.257Z",
            "tags": [],
            "classTitle": "Head",
            "points": {
                "exterior": [
                    [
                        674,
                        36
                    ],
                    [
                        714,
                        95
                    ]
                ],
                "interior": []
            }
        }
    ]
}